packitup/__init__.py
packitup/packitup.py
packitup-1.0.8.dist-info/LICENSE
packitup-1.0.8.dist-info/METADATA
packitup-1.0.8.dist-info/WHEEL
packitup-1.0.8.dist-info/entry_points.txt
packitup-1.0.8.dist-info/top_level.txt
packitup-1.0.8.dist-info/RECORD
