Metadata-Version: 2.1
Name: packitup
Version: 1.0.8
Summary: A tool to generate project structure and contents as Markdown
Home-page: https://github.com/jamesfincher/packitup
Author: James Fincher
Author-email: james@fincher.dev
Classifier: Programming Language :: Python :: 3
Classifier: Programming Language :: Python :: 3.6
Classifier: Programming Language :: Python :: 3.7
Classifier: Programming Language :: Python :: 3.8
Classifier: Programming Language :: Python :: 3.9
Classifier: Programming Language :: Python :: 3.10
Classifier: License :: OSI Approved :: MIT License
Classifier: Operating System :: OS Independent
Classifier: Intended Audience :: Developers
Classifier: Topic :: Software Development :: Documentation
Classifier: Topic :: Utilities
Requires-Python: >=3
License-File: LICENSE
Requires-Dist: pyperclip
Requires-Dist: colorama
Requires-Dist: pyyaml
Requires-Dist: tqdm
